{
  "title": "Gin5 · Oncoginecologia (endométrio/colo) · revisão para provas R1",
  "module": "gin5",
  "profiles": [
    {
      "id": "geral",
      "label": "Brasil",
      "kicker": "Estatística geral",
      "blurb": "Síntese de endométrio e colo/HPV.",
      "verdict": "No Gin5, o núcleo é rastreio do colo (MS 25–64), citologia/HSIL/conização, HPV/vacina e HE/CE (sangramento pós-meno + atipia). Oncoginecologia ~24% da Ginecologia na síntese Brasil.",
      "foco": "Rastreio colo · Citologia · HE/CE · HPV/vacina · Conização",
      "estilo": "Visão geral do que mais cai no Brasil",
      "priorities": [
        { "tema": "Rastreamento / citologia do colo", "pct": 26, "n": 26 },
        { "tema": "Hiperplasia / Ca de endométrio", "pct": 24, "n": 24 },
        { "tema": "NIC / conização / HSIL", "pct": 20, "n": 20 },
        { "tema": "HPV / vacina", "pct": 16, "n": 16 },
        { "tema": "Ca de colo invasor", "pct": 14, "n": 14 }
      ],
      "deckOrder": [
        "gin5-rastreamento-colo",
        "gin5-citologia",
        "gin5-hiperplasia",
        "gin5-ca-endometrio",
        "gin5-nic-tratamento",
        "gin5-hpv",
        "gin5-ca-colo"
      ],
      "checklist": ["rastreio", "cito", "he", "ce", "nic", "hpv"],
      "sessoes": [
        {
          "titulo": "Sessão 1 · Colo rastreio",
          "texto": "25–64, intervalo 3 anos, ASC-US/LSIL/HSIL."
        },
        {
          "titulo": "Sessão 2 · Endométrio",
          "texto": "Atipia → histerectomia; pós-meno sangra → investigar."
        },
        {
          "titulo": "Sessão 3 · HPV + cone",
          "texto": "Vacina 2 doses <15a; quando excisar."
        }
      ],
      "lacuna": "FIGO completo estádio a estádio de colo e endométrio: saiba a lógica (colo clínico × endométrio cirúrgico).",
      "sourceType": "sintese",
      "source": "Síntese de padrões de prova (colo ~10% top Enamed; onco ~24–27% em levantamentos) aplicada ao Gin5."
    },
    {
      "id": "enamed",
      "label": "Enamed",
      "kicker": "Nacional · acesso Enare",
      "featured": true,
      "blurb": "Padrão nacional INEP/Ebserh.",
      "verdict": "Enamed ama rastreio do colo e conduta citológica. Endométrio cai como sangramento pós-menopausa. Vacina HPV aparece em preventiva.",
      "foco": "Rastreio colo · Citologia · Pós-meno · Vacina HPV",
      "estilo": "Levantamento / padrão Enamed-Enare",
      "sourceType": "levantamento",
      "source": "Padrão Enamed/Enare (câncer de colo ~10% top) aplicado ao Gin5.",
      "priorities": [
        { "tema": "Rastreamento / citologia", "pct": 34 },
        { "tema": "HE / Ca endométrio", "pct": 22 },
        { "tema": "HPV / vacina", "pct": 18 },
        { "tema": "HSIL / conização", "pct": 16 },
        { "tema": "Ca colo invasor", "pct": 10 }
      ],
      "deckOrder": [
        "gin5-rastreamento-colo",
        "gin5-citologia",
        "gin5-ca-endometrio",
        "gin5-hiperplasia",
        "gin5-hpv",
        "gin5-nic-tratamento",
        "gin5-ca-colo"
      ],
      "checklist": ["rastreio", "cito", "ce", "hpv", "nic"],
      "sessoes": [
        {
          "titulo": "Sessão 1 · 25–64",
          "texto": "Intervalos do MS."
        },
        {
          "titulo": "Sessão 2 · Laudo alterado",
          "texto": "ASC-US vs HSIL."
        },
        {
          "titulo": "Sessão 3 · Pós-meno",
          "texto": "Sangra → endométrio."
        }
      ],
      "lacuna": "Todos os fluxogramas do apêndice INCA: foque as condutas iniciais."
    },
    {
      "id": "usp",
      "label": "USP",
      "kicker": "Fisiopatologia + fluxo",
      "blurb": "HE/CE e HPV com conceito.",
      "verdict": "USP pesa tipo I/II, atipia da HE, Lynch e estadiamento cirúrgico do endométrio. Colo aparece com história natural e Bethesda.",
      "foco": "HE/CE · Tipo I/II · Bethesda · HPV",
      "estilo": "Levantamento USP-SP",
      "sourceType": "levantamento",
      "source": "Padrão USP aplicado ao Gin5.",
      "priorities": [
        { "tema": "HE / Ca endométrio", "pct": 32 },
        { "tema": "Citologia / Bethesda", "pct": 22 },
        { "tema": "HPV / história natural", "pct": 18 },
        { "tema": "NIC / conização", "pct": 16 },
        { "tema": "Rastreio MS", "pct": 12 }
      ],
      "deckOrder": [
        "gin5-hiperplasia",
        "gin5-ca-endometrio",
        "gin5-citologia",
        "gin5-hpv",
        "gin5-nic-tratamento",
        "gin5-rastreamento-colo",
        "gin5-ca-colo"
      ],
      "checklist": ["he", "ce", "cito", "hpv", "nic"],
      "sessoes": [
        {
          "titulo": "Sessão 1 · Endométrio",
          "texto": "Atipia e tipo I/II."
        },
        {
          "titulo": "Sessão 2 · Bethesda",
          "texto": "LSIL vs HSIL."
        },
        {
          "titulo": "Sessão 3 · Cone",
          "texto": "Quando excisar."
        }
      ],
      "lacuna": "Mutações moleculares do CE: saiba Lynch e dualismo tipo I/II."
    },
    {
      "id": "unifesp",
      "label": "UNIFESP",
      "kicker": "Onco + conduta",
      "blurb": "Cirurgia e estadiamento.",
      "verdict": "Unifesp (onco alta) cobra estadiamento do CE, histerectomia+SOB, conização com indicação precisa e Ca de colo clínico vs cirúrgico.",
      "foco": "Estadiamento CE · Conização · Ca colo · HE atípica",
      "estilo": "Levantamento UNIFESP",
      "sourceType": "levantamento",
      "source": "Padrão UNIFESP (oncologia ~27%) aplicado ao Gin5.",
      "priorities": [
        { "tema": "Ca endométrio / estadiamento", "pct": 28 },
        { "tema": "NIC / conização", "pct": 24 },
        { "tema": "Ca colo", "pct": 20 },
        { "tema": "HE atípica", "pct": 16 },
        { "tema": "Rastreio / HPV", "pct": 12 }
      ],
      "deckOrder": [
        "gin5-ca-endometrio",
        "gin5-nic-tratamento",
        "gin5-ca-colo",
        "gin5-hiperplasia",
        "gin5-citologia",
        "gin5-hpv",
        "gin5-rastreamento-colo"
      ],
      "checklist": ["ce", "nic", "he", "cito", "hpv"],
      "sessoes": [
        {
          "titulo": "Sessão 1 · CE cirúrgico",
          "texto": "HTA + SOB + estádios."
        },
        {
          "titulo": "Sessão 2 · Excisão",
          "texto": "Indicações de cone."
        },
        {
          "titulo": "Sessão 3 · Colo invasor",
          "texto": "Estadiamento clínico."
        }
      ],
      "lacuna": "Linfadenectomia para-aórtica detalhada: só o conceito de estadiamento."
    },
    {
      "id": "enare",
      "label": "Enare",
      "kicker": "2021–2024",
      "blurb": "Direto e protocolar.",
      "verdict": "Enare cobra protocolo MS de colo, vacina HPV e sangramento pós-meno. Menos FIGO detalhado.",
      "foco": "Rastreio · Vacina · Pós-meno · HSIL",
      "estilo": "Levantamento Enare",
      "sourceType": "levantamento",
      "source": "Padrão Enare aplicado ao Gin5.",
      "priorities": [
        { "tema": "Rastreamento colo", "pct": 30 },
        { "tema": "Citologia / HSIL", "pct": 24 },
        { "tema": "HPV / vacina", "pct": 20 },
        { "tema": "HE / CE", "pct": 16 },
        { "tema": "Ca colo", "pct": 10 }
      ],
      "deckOrder": [
        "gin5-rastreamento-colo",
        "gin5-citologia",
        "gin5-hpv",
        "gin5-ca-endometrio",
        "gin5-hiperplasia",
        "gin5-nic-tratamento",
        "gin5-ca-colo"
      ],
      "checklist": ["rastreio", "cito", "hpv", "ce", "nic"],
      "sessoes": [
        {
          "titulo": "Sessão 1 · Protocolo",
          "texto": "Idade e intervalo."
        },
        {
          "titulo": "Sessão 2 · Laudo",
          "texto": "O que fazer no ASC-US/HSIL."
        },
        {
          "titulo": "Sessão 3 · Vacina + pós-meno",
          "texto": "2 doses e investigar sangramento."
        }
      ],
      "lacuna": "Nomenclatura antiga Papanicolaou I–V: use Bethesda/MS."
    }
  ],
  "checklistItems": {
    "rastreio": {
      "tema": "Rastreio do colo",
      "yield": "Máximo",
      "pegar": "25–64 anos · 2 anuais normais → 3/3 anos · Ecto+endo · Objetivo = achar HSIL"
    },
    "cito": {
      "tema": "Citologia",
      "yield": "Máximo",
      "pegar": "ASC-US → repetir/HPV · LSIL = baixo grau · HSIL/ASC-H → colposcopia · AGC → investigar sempre"
    },
    "he": {
      "tema": "Hiperplasia",
      "yield": "Máximo",
      "pegar": "Sem atipia: progestágeno · Com atipia: histerectomia (ou progestágeno se desejo gestacional) · Atipia = risco"
    },
    "ce": {
      "tema": "Ca endométrio",
      "yield": "Máximo",
      "pegar": "Pós-meno sangra → investigar · Tipo I vs II · Estadiamento cirúrgico · HTA+SOB · Lynch"
    },
    "nic": {
      "tema": "NIC / cone",
      "yield": "Alto",
      "pegar": "HSIL → colpo/biópsia · Cone se JEC− / discordância / suspeita invasão · Margem+ → follow-up estrito"
    },
    "hpv": {
      "tema": "HPV / vacina",
      "yield": "Alto",
      "pegar": "16/18 ~70% · Vacina 2 doses <15a · 3 doses se ≥15a ou imunossuprimido · Não dispensa rastreio"
    }
  },
  "numeros": [
    "Rastreio colo: 25–64 anos · intervalo de 3 anos após 2 normais anuais",
    "Progressão precursora → invasor: ~10–15 anos",
    "HPV 16+18 ≈ 70% dos Ca de colo",
    "HE → câncer: simples 1% · complexa 3% · atípica simples 8% · atípica complexa 29%",
    "CE: média ~60a · ~75% estádio I · sobrevida global ~80%",
    "Vacina <15a: 2 doses (0–6 meses)",
    "Imunossuprimidos: 3 doses 0-2-6 até 45a",
    "Estadiamento: colo = clínico · endométrio = cirúrgico"
  ],
  "pegadinhas": [
    "Colo = estadiamento clínico; endométrio = cirúrgico",
    "Sangramento pós-meno nunca é “normal do climatério” sem investigação",
    "HE sem atipia ≠ indicação automática de histerectomia",
    "Vacina não substitui Papanicolaou",
    "ASC-H não é ASC-US “um pouco pior” sem colposcopia",
    "AGC exige investigação de endocérvice/endométrio",
    "CIS só se confirma após cone (excluir invasão)",
    "Margem comprometida ≠ reoperar sempre",
    "“Câncer das avós” = endométrio; “das mães” = colo"
  ],
  "baixoRoi": [
    "Todas as proteínas E6/E7 em profundidade",
    "FIGO completo com subestádios memorizados",
    "Lista de todos os 12 HPV de alto risco",
    "Protocolos de braquiterapia dose a dose",
    "Classificações citológicas históricas completas"
  ],
  "unitLabel": "% das questões deste tema",
  "note": "Percentuais = participação de cada subtema dentro deste grupo (não da prova inteira)."
}
